mangosort/__init__.py
mangosort/mangosort.py
mangosort-0.2.1.dist-info/LICENSE
mangosort-0.2.1.dist-info/METADATA
mangosort-0.2.1.dist-info/WHEEL
mangosort-0.2.1.dist-info/top_level.txt
mangosort-0.2.1.dist-info/RECORD
