Metadata-Version: 2.1
Name: mangosort
Version: 0.2.1
Summary: Sort list by multiple keys and directions
Home-page: https://github.com/raulmangolin/mangosort
Author: Raul Mangolin
Author-email: eu@raulmangolin.com
License: MIT License
Keywords: dictionary dict list sort keysort
Platform: UNKNOWN
